Metadata-Version: 2.1
Name: solgate
Version: 3.5.5
Summary: A CLI tool for S3 data synchronizations.
Home-page: https://github.com/aicoe-aiops/sync-pipelines
Author: Tom Coufal
Author-email: tcoufal@redhat.com
Maintainer: Tom Coufal
Maintainer-email: tcoufal@redhat.com
License: GPLv3+
Platform: UNKNOWN
License-File: LICENSE
Requires-Dist: logstash-formatter (>=0.5.17)
Requires-Dist: s3fs (==0.4.*)
Requires-Dist: jinja2 (>=2.11)
Requires-Dist: click
Requires-Dist: pyyaml
Requires-Dist: boto3
Requires-Dist: backoff
